ejercicio 4/ffJK.v
module ffjk(input clk, input reset, input ena, input J,K, output logic q);

	always @ (posedge clk, posedge reset)
		if (reset)
			q <= 0;
		else if (ena==1 && J==0 && K==0)
			q <= q;	
		else if (ena==1 && J==1 && K==0)
			q <= 1;	
		else if (ena==1 && J==0 && K==1)
			q <= 0;	
		else if (ena==1 && J==1 && K==1)
			q <= ~q;			
endmodule

ejercicio 4/ffJK_tb.v
module testbench();

reg clk = 0;
reg reset = 0;
reg enabled = 0;
reg j, k;
output wire q1;

ffjk eins(clk, reset, enabled, j, k, q1);

initial begin
	   j=1; k=0;
	#1 reset=1; #1 reset=0;
	#1 enabled=1;
	#3 j=1; k=0;
	#3 j=0; k=1;
	#3 j=1; k=1;
	#6 j=0; k=0;
end



always@(*)begin
	#1 clk = ~clk;
end
always@(*)begin
	#1 clk = ~clk;
end
initial
	#25 $finish;		

initial begin
	$dumpfile("ffJK_tb.vcd");
	$dumpvars(0, testbench);
	end
endmodule

ejercicio 3/ffJK_tb.vcd
$date
	Thu Oct 29 16:16:06 2020
$end
$version
	Icarus Verilog
$end
$timescale
	1ps
$end
$scope module testbench $end
$var wire 1 ! q1 $end
$var reg 1 " clk $end
$var reg 1 # enabled $end
$var reg 1 $ j $end
$var reg 1 % k $end
$var reg 1 & reset $end
$scope module eins $end
$var wire 1 $ J $end
$var wire 1 % K $end
$var wire 1 " clk $end
$var wire 1 # ena $end
$var wire 1 & reset $end
$var reg 1 ! q $end
$upscope $end
$upscope $end
$enddefinitions $end
#0
$dumpvars
0&
0%
1$
0#
0"
x!
$end
#1
0!
0"
1&
#2
1"
0&
#3
0"
1#
#4
1!
1"
#5
0"
#6
1"
#7
0"
#8
1"
#9
0"
1%
0$
#10
0!
1"
#11
0"
#12
1!
1"
1$
#13
0"
#14
0!
1"
#15
0"
#16
1!
1"
#17
0"
#18
1"
0%
0$
