ejercicio 5/ROMcase.v
module ROM(input wire [6:0]addr, output logic [12:0]data);

reg[12:0] dato;

	always @(*) begin
		casez (addr)
			7'b??????0:
		 		dato = 13'b1000000001000;
			7'b00001?1: dato = 13'b0100000001000;
			7'b00000?1: dato = 13'b1000000001000;
			7'b00011?1: dato = 13'b1000000001000;
			7'b00010?1: dato = 13'b0100000001000;
			7'b0010??1: dato = 13'b0001001000010;
			7'b0011??1: dato = 13'b1001001100000;
			7'b0100??1: dato = 13'b0011010000010;
			7'b0101??1: dato = 13'b0011010000100;
			7'b0110??1: dato = 13'b1011010100000;
			7'b0111??1: dato = 13'b1000000111000;
			7'b1000?11: dato = 13'b0100000001000;
			7'b1000?01: dato = 13'b1000000001000;
			7'b1001?11: dato = 13'b1000000001000;
			7'b1001?01: dato = 13'b0100000001000;
			7'b1010??1: dato = 13'b0011011000010;
			7'b1011??1: dato = 13'b1011011100000;
			7'b1100??1: dato = 13'b0100000001000;
			7'b1101??1: dato = 13'b0000000001001;
			7'b1110??1: dato = 13'b0011100000010;
			7'b1111??1: dato = 13'b1011100100000;
			default: dato = 13'bxxxxxxxxxxxxx;			
		endcase
		assign data = dato;
end
endmodule

ejercicio 5/ROMcase_tb.v
module testbench();

reg [6:0]addres;
output wire [12:0]dato;

ROM zucker(addres, dato);

initial begin
	   addres = 7'b0000000;
	#1 $display("Address = %b, dato = %b", addres, dato);
	
	#1 addres = 7'b0000101;
	#1 $display("Address = %b, dato = %b", addres, dato);
	
	#1 addres = 7'b0000001;
	#1 $display("Address = %b, dato = %b", addres, dato);

	#1 addres = 7'b0001101;
	#1 $display("Address = %b, dato = %b", addres, dato);

	#1 addres = 7'b0001001;
	#1 $display("Address = %b, dato = %b", addres, dato);

	#1 addres = 7'b0010001;
	#1 $display("Address = %b, dato = %b", addres, dato);

	#1 addres = 7'b0011001;
	#1 $display("Address = %b, dato = %b", addres, dato);

	#1 addres = 7'b0100001;
	#1 $display("Address = %b, dato = %b", addres, dato);

	#1 addres = 7'b0101001;
	#1 $display("Address = %b, dato = %b", addres, dato);

	#1 addres = 7'b0110001;
	#1 $display("Address = %b, dato = %b", addres, dato);

	#1 addres = 7'b0111001;
	#1 $display("Address = %b, dato = %b", addres, dato);

	#1 addres = 7'b1000011;
	#1 $display("Address = %b, dato = %b", addres, dato);

	#1 addres = 7'b1000001;
	#1 $display("Address = %b, dato = %b", addres, dato);

	#1 addres = 7'b1001011;
	#1 $display("Address = %b, dato = %b", addres, dato);

	#1 addres = 7'b1001001;
	#1 $display("Address = %b, dato = %b", addres, dato);

	#1 addres = 7'b1010001;
	#1 $display("Address = %b, dato = %b", addres, dato);

	#1 addres = 7'b1011001;
	#1 $display("Address = %b, dato = %b", addres, dato);

	#1 addres = 7'b1100001;
	#1 $display("Address = %b, dato = %b", addres, dato);

	#1 addres = 7'b1101001;
	#1 $display("Address = %b, dato = %b", addres, dato);

	#1 addres = 7'b1110001;
	#1 $display("Address = %b, dato = %b", addres, dato);

	#1 addres = 7'b1111001;
	#1 $display("Address = %b, dato = %b", addres, dato);

end



initial
	#25 $finish;		
initial begin
	$dumpfile("ROMcase_tb.vcd");
	$dumpvars(0, testbench);
	end
endmodule

ejercicio 5/ROMcase_tb.vcd
$date
	Thu Oct 29 18:54:43 2020
$end
$version
	Icarus Verilog
$end
$timescale
	1ps
$end
$scope module testbench $end
$var wire 13 ! dato [12:0] $end
$var reg 7 " addres [6:0] $end
$scope module zucker $end
$var wire 7 # addr [6:0] $end
$var reg 13 $ data [12:0] $end
$var reg 13 % dato [12:0] $end
$upscope $end
$upscope $end
$enddefinitions $end
#0
$dumpvars
b1000000001000 %
b1000000001000 $
b0 #
b0 "
b1000000001000 !
$end
#2
b100000001000 !
b100000001000 $
b100000001000 %
b101 "
b101 #
#4
b1000000001000 !
b1000000001000 $
b1000000001000 %
b1 "
b1 #
#6
b1101 "
b1101 #
#8
b100000001000 !
b100000001000 $
b100000001000 %
b1001 "
b1001 #
#10
b1001000010 !
b1001000010 $
b1001000010 %
b10001 "
b10001 #
#12
b1001001100000 !
b1001001100000 $
b1001001100000 %
b11001 "
b11001 #
#14
b11010000010 !
b11010000010 $
b11010000010 %
b100001 "
b100001 #
#16
b11010000100 !
b11010000100 $
b11010000100 %
b101001 "
b101001 #
#18
b1011010100000 !
b1011010100000 $
b1011010100000 %
b110001 "
b110001 #
#20
b1000000111000 !
b1000000111000 $
b1000000111000 %
b111001 "
b111001 #
#22
b100000001000 !
b100000001000 $
b100000001000 %
b1000011 "
b1000011 #
#24
b1000000001000 !
b1000000001000 $
b1000000001000 %
b1000001 "
b1000001 #
