ejercicio 2/ffT.v
module ffd1(input clk, input reset, input ena, input d, output logic q);

	always @ (posedge clk, posedge reset)
		if (reset)
			q <= d;
		else if (ena)
			q <= ~d;			
endmodule

module ffd2(input clk, input reset, input ena, input [1:0]d, output logic [1:0]q);

	always @ (posedge clk, posedge reset)
		if (reset)
			q <= d;
		else if (ena)
			q <= ~d;			
endmodule

module ffd4(input clk, input reset, input ena, input [3:0]d, output logic [3:0]q);

	always @ (posedge clk, posedge reset)
		if (reset)
			q <= d;
		else if (ena)
			q <= ~d;			
endmodule

ejercicio 2/ffT_tb.v
module testbench();

reg clk = 0;
reg reset = 0;
reg enabled = 0;
reg d1;
reg [1:0]d2;
reg [3:0]d4;
output wire q1;
output wire[1:0]q2;
output wire[3:0]q4;

ffd1 eins(clk, reset, enabled, d1, q1);
ffd2 zweis(clk, reset, enabled, d2, q2);
ffd4 vier(clk, reset, enabled, d4, q4);

initial begin
       reset=1; #1 reset = 0; enabled=1; reset=1; #1 reset = 0;
     #2 d1=1'b1; d2=2'b10;  d4=4'b1010; 
     #2 d1=1'b0; d2=2'b00;  d4=4'b1110; 
     #2 d1=1'b1; d2=2'b01;  d4=4'b1011; 
     #2 d1=1'b1; d2=2'b11;  d4=4'b1100; 
     #2 d1=1'b0; d2=2'b10;  d4=4'b1111;
     #2 d1=1'b1; d2=2'b11;  d4=4'b0001; 
     #2 d1=1'b0; d2=2'b11;  d4=4'b1110; 
     #2 d1=1'b1; d2=2'b10;  d4=4'b1101;

end



always@(*)begin
	#1 clk = ~clk;
end
always@(*)begin
	#1 clk = ~clk;
end

initial
	#20 $finish;		

initial begin
	$dumpfile("ffT_tb.vcd");
	$dumpvars(0, testbench);
	end
endmodule

ejercicio 2/ffT_tb.vcd
$date
	Thu Oct 29 14:00:24 2020
$end
$version
	Icarus Verilog
$end
$timescale
	1ps
$end
$scope module testbench $end
$var wire 4 ! q4 [3:0] $end
$var wire 2 " q2 [1:0] $end
$var wire 1 # q1 $end
$var reg 1 $ clk $end
$var reg 1 % d1 $end
$var reg 2 & d2 [1:0] $end
$var reg 4 ' d4 [3:0] $end
$var reg 1 ( enabled $end
$var reg 1 ) reset $end
$scope module eins $end
$var wire 1 $ clk $end
$var wire 1 % d $end
$var wire 1 ( ena $end
$var wire 1 ) reset $end
$var reg 1 # q $end
$upscope $end
$scope module vier $end
$var wire 1 $ clk $end
$var wire 4 * d [3:0] $end
$var wire 1 ( ena $end
$var wire 1 ) reset $end
$var reg 4 + q [3:0] $end
$upscope $end
$scope module zweis $end
$var wire 1 $ clk $end
$var wire 2 , d [1:0] $end
$var wire 1 ( ena $end
$var wire 1 ) reset $end
$var reg 2 - q [1:0] $end
$upscope $end
$upscope $end
$enddefinitions $end
#0
$dumpvars
bx -
bx ,
bx +
bx *
1)
0(
bx '
bx &
x%
0$
x#
bx "
bx !
$end
#1
0$
1(
1)
#2
1$
0)
#3
0$
#4
b101 !
b101 +
b1 "
b1 -
0#
1$
b1010 '
b1010 *
b10 &
b10 ,
1%
#5
0$
#6
1#
b11 "
b11 -
b1 !
b1 +
1$
b1110 '
b1110 *
b0 &
b0 ,
0%
#7
0$
#8
b100 !
b100 +
b10 "
b10 -
0#
1$
b1011 '
b1011 *
b1 &
b1 ,
1%
#9
0$
#10
b0 "
b0 -
b11 !
b11 +
1$
b1100 '
b1100 *
b11 &
b11 ,
#11
0$
#12
b0 !
b0 +
b1 "
b1 -
1#
1$
b1111 '
b1111 *
b10 &
b10 ,
0%
#13
0$
#14
0#
b0 "
b0 -
b1110 !
b1110 +
1$
b1 '
b1 *
b11 &
b11 ,
1%
#15
0$
#16
b1 !
b1 +
1#
1$
b1110 '
b1110 *
0%
#17
0$
#18
0#
b1 "
b1 -
b10 !
b10 +
1$
b1101 '
b1101 *
b10 &
b10 ,
1%
