ejercicio 2/ffT.v
module ffT1(input clk, input reset, input ena, output logic q);
reg d;
	always @ (posedge clk, posedge reset)
		if (reset)
			q <= 0;
		else if (ena)
			q <= ~q;			
endmodule

ejercicio 2/ffT_tb.v
module testbench();

reg clk = 0;
reg reset = 0;
reg enabled = 0;

output wire q1;


ffT1 eins(clk, reset, enabled, q1);

initial begin
	   enabled=1; 
       	#3 reset=1; #1 reset = 0; 
       	#6 reset=1; #1 reset = 0; 
	#1 enabled=0; #3 enabled=1;  
end



always@(*)begin
	#1 clk = ~clk;
end
always@(*)begin
	#1 clk = ~clk;
end

initial
	#20 $finish;		

initial begin
	$dumpfile("ffT_tb.vcd");
	$dumpvars(0, testbench);
	end
endmodule

ejercicio 2/ffT_tb.vcd
$date
	Thu Oct 29 15:13:02 2020
$end
$version
	Icarus Verilog
$end
$timescale
	1ps
$end
$scope module testbench $end
$var wire 1 ! q1 $end
$var reg 1 " clk $end
$var reg 1 # enabled $end
$var reg 1 $ reset $end
$scope module eins $end
$var wire 1 " clk $end
$var wire 1 # ena $end
$var wire 1 $ reset $end
$var reg 1 ! q $end
$upscope $end
$upscope $end
$enddefinitions $end
#0
$dumpvars
0$
1#
0"
x!
$end
#1
0"
#2
1"
#3
0!
0"
1$
#4
1!
1"
0$
#5
0"
#6
0!
1"
#7
0"
#8
1!
1"
#9
0"
#10
0!
1"
1$
#11
0"
0$
#12
1"
0#
#13
0"
#14
1"
#15
0"
1#
#16
1!
1"
#17
0"
#18
0!
1"
#19
0"
#20
1!
1"
